django_radius_eap_mschapv2_authbackend/EAPMSCHAPv2RADIUSBackend.py
django_radius_eap_mschapv2_authbackend/__init__.py
django_radius_eap_mschapv2_authbackend-1.0.dist-info/LICENSE
django_radius_eap_mschapv2_authbackend-1.0.dist-info/METADATA
django_radius_eap_mschapv2_authbackend-1.0.dist-info/WHEEL
django_radius_eap_mschapv2_authbackend-1.0.dist-info/top_level.txt
django_radius_eap_mschapv2_authbackend-1.0.dist-info/RECORD
