Metadata-Version: 2.1
Name: django-radius-eap-mschapv2-authbackend
Version: 1.0
Summary: A Django RADIUS EAP-MSCHAPv2 Authentication Backend
Home-page: https://github.com/mneitsabes/RADIUS-EAP-MSCHAPv2-Python-client
Author: mneitsabes
Author-email: mneitsabes@nulloz.be
License: UNKNOWN
Keywords: radius,EAP,MSCHAPv2,django,backend,auth
Platform: UNKNOWN
Classifier: Programming Language :: Python :: 3
Classifier: License :: OSI Approved :: MIT License
Classifier: Operating System :: OS Independent
Requires-Python: >=3.6
Requires-Dist: radius-eap-mschapv2-client
